refib/__init__.py
refib/core.py
refib-0.1.0.dist-info/licenses/LICENSE
refib-0.1.0.dist-info/METADATA
refib-0.1.0.dist-info/WHEEL
refib-0.1.0.dist-info/top_level.txt
refib-0.1.0.dist-info/RECORD
