Metadata-Version: 2.4
Name: refib
Version: 0.1.0
Summary: A simple Python retry library using Fibonacci sequence delays
Home-page: https://github.com/uncorrelited/refib
Author: David Li
Author-email: David Li <uncorrelited@fastmail.com>
License: MIT
Project-URL: Homepage, https://github.com/uncorrelited/refib
Project-URL: Bug Tracker, https://github.com/uncorrelited/refib/issues
Project-URL: Source Code, https://github.com/uncorrelited/refib
Keywords: retry,fibonacci,backoff,decorator,resilience,fault-tolerance
Classifier: Development Status :: 4 - Beta
Classifier: Intended Audience :: Developers
Classifier: Programming Language :: Python :: 3
Classifier: Programming Language :: Python :: 3.6
Classifier: Programming Language :: Python :: 3.7
Classifier: Programming Language :: Python :: 3.8
Classifier: Programming Language :: Python :: 3.9
Classifier: Programming Language :: Python :: 3.10
Classifier: Programming Language :: Python :: 3.11
Classifier: Programming Language :: Python :: 3.12
Classifier: Programming Language :: Python :: 3.13
Classifier: Operating System :: OS Independent
Classifier: Topic :: Software Development :: Libraries :: Python Modules
Requires-Python: >=3.6
License-File: LICENSE
Provides-Extra: dev
Requires-Dist: pytest>=6.0; extra == "dev"
Requires-Dist: pytest-cov>=2.0; extra == "dev"
Requires-Dist: pytest-timeout>=1.4; extra == "dev"
Requires-Dist: black>=22.3.0; extra == "dev"
Requires-Dist: flake8>=4.0; extra == "dev"
Requires-Dist: mypy>=0.910; extra == "dev"
Requires-Dist: tox>=3.24; extra == "dev"
Dynamic: author
Dynamic: home-page
Dynamic: license-file
Dynamic: requires-python
